prophecy_provider/__init__.py
prophecy_provider/emailer.py
apache_airflow_providers_prophecy-1.0.1.dist-info/METADATA
apache_airflow_providers_prophecy-1.0.1.dist-info/WHEEL
apache_airflow_providers_prophecy-1.0.1.dist-info/entry_points.txt
apache_airflow_providers_prophecy-1.0.1.dist-info/top_level.txt
apache_airflow_providers_prophecy-1.0.1.dist-info/RECORD
